{"images/coloring1.png":["images/coloring1.png"],"images/phase0.png":["images/phase0.png"],"images/phase1.png":["images/phase1.png"],"images/phase2.png":["images/phase2.png"],"images/phase3.png":["images/phase3.png"],"images/phase4.png":["images/phase4.png"],"images/phase5.png":["images/phase5.png"],"images/pusheen.png":["images/pusheen.png"],"packages/cupertino_icons/assets/CupertinoIcons.ttf":["packages/cupertino_icons/assets/CupertinoIcons.ttf"],"packages/record_web/assets/js/record.worklet.js":["packages/record_web/assets/js/record.worklet.js"]}